CHANGELOG
MANIFEST.in
README.rst
setup.py
datetime_periods/__init__.py
datetime_periods/period.py
datetime_periods/period_end.py
datetime_periods/sugar.py
datetime_periods/time_range.py
datetime_periods.egg-info/PKG-INFO
datetime_periods.egg-info/SOURCES.txt
datetime_periods.egg-info/dependency_links.txt
datetime_periods.egg-info/requires.txt
datetime_periods.egg-info/top_level.txt