Metadata-Version: 1.1
Name: datetime-periods
Version: 1.1.1
Summary: Easily create time periods from timestamps
Home-page: https://github.com/gaqzi/datetime_periods
Author: Björn Andersson
Author-email: ba@sanitarium.se
License: BSD
Platform: UNKNOWN
Classifier: Intended Audience :: Developers
Classifier: License :: OSI Approved :: BSD License
Classifier: Programming Language :: Python
